{
    "@context": "http://enpaku-jdta.jp/api-context",
    "@id": "http://enpaku-jdta.jp/api/items/234557",
    "@type": "o:Item",
    "dcepk:actor": [
        {
            "@id": "http://enpaku-jdta.jp/api/items/219843",
            "display_title": "リー５世",
            "is_public": true,
            "property_id": 486,
            "property_label": "出演者",
            "type": "resource",
            "url": null,
            "value_resource_id": 219843,
            "value_resource_name": "items"
        },
        {
            "@id": "http://enpaku-jdta.jp/api/items/219844",
            "display_title": "高山のえみ",
            "is_public": true,
            "property_id": 486,
            "property_label": "出演者",
            "type": "resource",
            "url": null,
            "value_resource_id": 219844,
            "value_resource_name": "items"
        },
        {
            "@id": "http://enpaku-jdta.jp/api/items/219845",
            "display_title": "坂口涼太郎",
            "is_public": true,
            "property_id": 486,
            "property_label": "出演者",
            "type": "resource",
            "url": null,
            "value_resource_id": 219845,
            "value_resource_name": "items"
        },
        {
            "@id": "http://enpaku-jdta.jp/api/items/219846",
            "display_title": "岡野康弘",
            "is_public": true,
            "property_id": 486,
            "property_label": "出演者",
            "type": "resource",
            "url": null,
            "value_resource_id": 219846,
            "value_resource_name": "items"
        },
        {
            "@id": "http://enpaku-jdta.jp/api/items/219847",
            "display_title": "亀島一徳",
            "is_public": true,
            "property_id": 486,
            "property_label": "出演者",
            "type": "resource",
            "url": null,
            "value_resource_id": 219847,
            "value_resource_name": "items"
        },
        {
            "@id": "http://enpaku-jdta.jp/api/items/219848",
            "display_title": "重岡漠",
            "is_public": true,
            "property_id": 486,
            "property_label": "出演者",
            "type": "resource",
            "url": null,
            "value_resource_id": 219848,
            "value_resource_name": "items"
        },
        {
            "@id": "http://enpaku-jdta.jp/api/items/219849",
            "display_title": "大柿友哉",
            "is_public": true,
            "property_id": 486,
            "property_label": "出演者",
            "type": "resource",
            "url": null,
            "value_resource_id": 219849,
            "value_resource_name": "items"
        }
    ],
    "dcepk:sourceIdentifier": [
        {
            "@value": "09667-01-2016-02:1-1",
            "is_public": true,
            "property_id": 516,
            "property_label": "ソースID",
            "type": "literal"
        }
    ],
    "dcepk:titleTranscription": [
        {
            "@language": "ja",
            "@value": "かんじんちょう",
            "is_public": true,
            "property_id": 517,
            "property_label": "公演名よみ",
            "type": "literal"
        }
    ],
    "dcterms:contributor": [
        {
            "@id": "http://enpaku-jdta.jp/api/items/231047",
            "display_title": "歌舞伎十八番の内",
            "is_public": true,
            "property_id": 6,
            "property_label": "Contributor",
            "type": "resource",
            "url": null,
            "value_resource_id": 231047,
            "value_resource_name": "items"
        },
        {
            "@id": "http://enpaku-jdta.jp/api/items/231048",
            "display_title": "木ノ下裕一",
            "is_public": true,
            "property_id": 6,
            "property_label": "Contributor",
            "type": "resource",
            "url": null,
            "value_resource_id": 231048,
            "value_resource_name": "items"
        },
        {
            "@id": "http://enpaku-jdta.jp/api/items/231049",
            "display_title": "杉原邦生",
            "is_public": true,
            "property_id": 6,
            "property_label": "Contributor",
            "type": "resource",
            "url": null,
            "value_resource_id": 231049,
            "value_resource_name": "items"
        },
        {
            "@id": "http://enpaku-jdta.jp/api/items/231050",
            "display_title": "Taichi Master",
            "is_public": true,
            "property_id": 6,
            "property_label": "Contributor",
            "type": "resource",
            "url": null,
            "value_resource_id": 231050,
            "value_resource_name": "items"
        },
        {
            "@id": "http://enpaku-jdta.jp/api/items/231051",
            "display_title": "木皮成",
            "is_public": true,
            "property_id": 6,
            "property_label": "Contributor",
            "type": "resource",
            "url": null,
            "value_resource_id": 231051,
            "value_resource_name": "items"
        },
        {
            "@id": "http://enpaku-jdta.jp/api/items/231052",
            "display_title": "大鹿展明",
            "is_public": true,
            "property_id": 6,
            "property_label": "Contributor",
            "type": "resource",
            "url": null,
            "value_resource_id": 231052,
            "value_resource_name": "items"
        },
        {
            "@id": "http://enpaku-jdta.jp/api/items/231053",
            "display_title": "伊藤泰行",
            "is_public": true,
            "property_id": 6,
            "property_label": "Contributor",
            "type": "resource",
            "url": null,
            "value_resource_id": 231053,
            "value_resource_name": "items"
        },
        {
            "@id": "http://enpaku-jdta.jp/api/items/231054",
            "display_title": "星野大輔",
            "is_public": true,
            "property_id": 6,
            "property_label": "Contributor",
            "type": "resource",
            "url": null,
            "value_resource_id": 231054,
            "value_resource_name": "items"
        },
        {
            "@id": "http://enpaku-jdta.jp/api/items/231055",
            "display_title": "藤谷香子",
            "is_public": true,
            "property_id": 6,
            "property_label": "Contributor",
            "type": "resource",
            "url": null,
            "value_resource_id": 231055,
            "value_resource_name": "items"
        },
        {
            "@id": "http://enpaku-jdta.jp/api/items/231056",
            "display_title": "若狭彰珠",
            "is_public": true,
            "property_id": 6,
            "property_label": "Contributor",
            "type": "resource",
            "url": null,
            "value_resource_id": 231056,
            "value_resource_name": "items"
        },
        {
            "@id": "http://enpaku-jdta.jp/api/items/231057",
            "display_title": "稲垣貴俊",
            "is_public": true,
            "property_id": 6,
            "property_label": "Contributor",
            "type": "resource",
            "url": null,
            "value_resource_id": 231057,
            "value_resource_name": "items"
        },
        {
            "@id": "http://enpaku-jdta.jp/api/items/231058",
            "display_title": "岩澤哲野",
            "is_public": true,
            "property_id": 6,
            "property_label": "Contributor",
            "type": "resource",
            "url": null,
            "value_resource_id": 231058,
            "value_resource_name": "items"
        },
        {
            "@id": "http://enpaku-jdta.jp/api/items/231059",
            "display_title": "山道弥栄",
            "is_public": true,
            "property_id": 6,
            "property_label": "Contributor",
            "type": "resource",
            "url": null,
            "value_resource_id": 231059,
            "value_resource_name": "items"
        },
        {
            "@id": "http://enpaku-jdta.jp/api/items/231060",
            "display_title": "関 亜弓",
            "is_public": true,
            "property_id": 6,
            "property_label": "Contributor",
            "type": "resource",
            "url": null,
            "value_resource_id": 231060,
            "value_resource_name": "items"
        },
        {
            "@id": "http://enpaku-jdta.jp/api/items/231061",
            "display_title": "外山 央",
            "is_public": true,
            "property_id": 6,
            "property_label": "Contributor",
            "type": "resource",
            "url": null,
            "value_resource_id": 231061,
            "value_resource_name": "items"
        },
        {
            "@id": "http://enpaku-jdta.jp/api/items/231062",
            "display_title": "本郷麻衣",
            "is_public": true,
            "property_id": 6,
            "property_label": "Contributor",
            "type": "resource",
            "url": null,
            "value_resource_id": 231062,
            "value_resource_name": "items"
        },
        {
            "@id": "http://enpaku-jdta.jp/api/items/231063",
            "display_title": "一般財団法人松本市芸術文化振興財団",
            "is_public": true,
            "property_id": 6,
            "property_label": "Contributor",
            "type": "resource",
            "url": null,
            "value_resource_id": 231063,
            "value_resource_name": "items"
        },
        {
            "@id": "http://enpaku-jdta.jp/api/items/231064",
            "display_title": "公益財団法人豊橋文化振興財団",
            "is_public": true,
            "property_id": 6,
            "property_label": "Contributor",
            "type": "resource",
            "url": null,
            "value_resource_id": 231064,
            "value_resource_name": "items"
        },
        {
            "@id": "http://enpaku-jdta.jp/api/items/231065",
            "display_title": "KYOTO EXPERIMENTほか",
            "is_public": true,
            "property_id": 6,
            "property_label": "Contributor",
            "type": "resource",
            "url": null,
            "value_resource_id": 231065,
            "value_resource_name": "items"
        },
        {
            "@id": "http://enpaku-jdta.jp/api/items/231066",
            "display_title": "北九州芸術劇場",
            "is_public": true,
            "property_id": 6,
            "property_label": "Contributor",
            "type": "resource",
            "url": null,
            "value_resource_id": 231066,
            "value_resource_name": "items"
        },
        {
            "@id": "http://enpaku-jdta.jp/api/items/231067",
            "display_title": "木ノ下歌舞伎",
            "is_public": true,
            "property_id": 6,
            "property_label": "Contributor",
            "type": "resource",
            "url": null,
            "value_resource_id": 231067,
            "value_resource_name": "items"
        },
        {
            "@id": "http://enpaku-jdta.jp/api/items/231068",
            "display_title": "堀朝美",
            "is_public": true,
            "property_id": 6,
            "property_label": "Contributor",
            "type": "resource",
            "url": null,
            "value_resource_id": 231068,
            "value_resource_name": "items"
        }
    ],
    "dcterms:identifier": [
        {
            "@value": "pg-ee519d0d58240db5cf65903eae92a75c",
            "is_public": true,
            "property_id": 10,
            "property_label": "Identifier",
            "type": "literal"
        },
        {
            "@value": "pg-ee519d0d58240db5cf65903eae92a75c",
            "is_public": true,
            "property_id": 10,
            "property_label": "Identifier",
            "type": "literal"
        }
    ],
    "dcterms:title": [
        {
            "@language": "ja",
            "@value": "勧進帳",
            "is_public": true,
            "property_id": 1,
            "property_label": "Title",
            "type": "literal"
        },
        {
            "@language": "en",
            "@value": "Kanjincho",
            "is_public": true,
            "property_id": 1,
            "property_label": "Title",
            "type": "literal"
        }
    ],
    "dcterms:type": [
        {
            "@value": "http://purl.org/dc/dcmitype/MovingImage",
            "is_public": true,
            "property_id": 8,
            "property_label": "Type",
            "type": "literal"
        }
    ],
    "o:created": {
        "@type": "http://www.w3.org/2001/XMLSchema#dateTime",
        "@value": "2021-02-19T12:18:54+00:00"
    },
    "o:id": 234557,
    "o:is_public": true,
    "o:item_set": [],
    "o:media": [],
    "o:modified": {
        "@type": "http://www.w3.org/2001/XMLSchema#dateTime",
        "@value": "2021-02-20T04:22:27+00:00"
    },
    "o:owner": {
        "@id": "http://enpaku-jdta.jp/api/users/1",
        "o:id": 1
    },
    "o:resource_class": null,
    "o:resource_template": {
        "@id": "http://enpaku-jdta.jp/api/resource_templates/10",
        "o:id": 10
    },
    "o:site": [
        {
            "@id": "http://enpaku-jdta.jp/api/sites/1",
            "o:id": 1
        }
    ],
    "o:thumbnail": null,
    "o:title": "勧進帳",
    "thumbnail_display_urls": {
        "large": null,
        "medium": null,
        "square": null
    }
}