{
    "@context": "http://enpaku-jdta.jp/api-context",
    "@id": "http://enpaku-jdta.jp/api/items/234791",
    "@type": "o:Item",
    "dcepk:actor": [
        {
            "@id": "http://enpaku-jdta.jp/api/items/217005",
            "display_title": "峯村リエ",
            "is_public": true,
            "property_id": 486,
            "property_label": "出演者",
            "type": "resource",
            "url": null,
            "value_resource_id": 217005,
            "value_resource_name": "items"
        },
        {
            "@id": "http://enpaku-jdta.jp/api/items/217006",
            "display_title": "大倉孝二",
            "is_public": true,
            "property_id": 486,
            "property_label": "出演者",
            "type": "resource",
            "url": null,
            "value_resource_id": 217006,
            "value_resource_name": "items"
        },
        {
            "@id": "http://enpaku-jdta.jp/api/items/217007",
            "display_title": "みのすけ",
            "is_public": true,
            "property_id": 486,
            "property_label": "出演者",
            "type": "resource",
            "url": null,
            "value_resource_id": 217007,
            "value_resource_name": "items"
        },
        {
            "@id": "http://enpaku-jdta.jp/api/items/217008",
            "display_title": "松永玲子",
            "is_public": true,
            "property_id": 486,
            "property_label": "出演者",
            "type": "resource",
            "url": null,
            "value_resource_id": 217008,
            "value_resource_name": "items"
        },
        {
            "@id": "http://enpaku-jdta.jp/api/items/217009",
            "display_title": "長田奈麻",
            "is_public": true,
            "property_id": 486,
            "property_label": "出演者",
            "type": "resource",
            "url": null,
            "value_resource_id": 217009,
            "value_resource_name": "items"
        },
        {
            "@id": "http://enpaku-jdta.jp/api/items/217010",
            "display_title": "新谷真弓",
            "is_public": true,
            "property_id": 486,
            "property_label": "出演者",
            "type": "resource",
            "url": null,
            "value_resource_id": 217010,
            "value_resource_name": "items"
        },
        {
            "@id": "http://enpaku-jdta.jp/api/items/217011",
            "display_title": "安澤千草",
            "is_public": true,
            "property_id": 486,
            "property_label": "出演者",
            "type": "resource",
            "url": null,
            "value_resource_id": 217011,
            "value_resource_name": "items"
        },
        {
            "@id": "http://enpaku-jdta.jp/api/items/217012",
            "display_title": "廣川三憲",
            "is_public": true,
            "property_id": 486,
            "property_label": "出演者",
            "type": "resource",
            "url": null,
            "value_resource_id": 217012,
            "value_resource_name": "items"
        },
        {
            "@id": "http://enpaku-jdta.jp/api/items/217013",
            "display_title": "藤田秀世",
            "is_public": true,
            "property_id": 486,
            "property_label": "出演者",
            "type": "resource",
            "url": null,
            "value_resource_id": 217013,
            "value_resource_name": "items"
        },
        {
            "@id": "http://enpaku-jdta.jp/api/items/217014",
            "display_title": "喜安浩平",
            "is_public": true,
            "property_id": 486,
            "property_label": "出演者",
            "type": "resource",
            "url": null,
            "value_resource_id": 217014,
            "value_resource_name": "items"
        },
        {
            "@id": "http://enpaku-jdta.jp/api/items/217015",
            "display_title": "大山鎬則",
            "is_public": true,
            "property_id": 486,
            "property_label": "出演者",
            "type": "resource",
            "url": null,
            "value_resource_id": 217015,
            "value_resource_name": "items"
        },
        {
            "@id": "http://enpaku-jdta.jp/api/items/217016",
            "display_title": "吉増裕士",
            "is_public": true,
            "property_id": 486,
            "property_label": "出演者",
            "type": "resource",
            "url": null,
            "value_resource_id": 217016,
            "value_resource_name": "items"
        },
        {
            "@id": "http://enpaku-jdta.jp/api/items/217017",
            "display_title": "杉山薫",
            "is_public": true,
            "property_id": 486,
            "property_label": "出演者",
            "type": "resource",
            "url": null,
            "value_resource_id": 217017,
            "value_resource_name": "items"
        },
        {
            "@id": "http://enpaku-jdta.jp/api/items/217018",
            "display_title": "植木夏十",
            "is_public": true,
            "property_id": 486,
            "property_label": "出演者",
            "type": "resource",
            "url": null,
            "value_resource_id": 217018,
            "value_resource_name": "items"
        },
        {
            "@id": "http://enpaku-jdta.jp/api/items/217019",
            "display_title": "皆戸麻衣",
            "is_public": true,
            "property_id": 486,
            "property_label": "出演者",
            "type": "resource",
            "url": null,
            "value_resource_id": 217019,
            "value_resource_name": "items"
        },
        {
            "@id": "http://enpaku-jdta.jp/api/items/217020",
            "display_title": "柚木幹斗",
            "is_public": true,
            "property_id": 486,
            "property_label": "出演者",
            "type": "resource",
            "url": null,
            "value_resource_id": 217020,
            "value_resource_name": "items"
        },
        {
            "@id": "http://enpaku-jdta.jp/api/items/217021",
            "display_title": "佐藤誓",
            "is_public": true,
            "property_id": 486,
            "property_label": "出演者",
            "type": "resource",
            "url": null,
            "value_resource_id": 217021,
            "value_resource_name": "items"
        },
        {
            "@id": "http://enpaku-jdta.jp/api/items/217022",
            "display_title": "志賀廣太郎",
            "is_public": true,
            "property_id": 486,
            "property_label": "出演者",
            "type": "resource",
            "url": null,
            "value_resource_id": 217022,
            "value_resource_name": "items"
        },
        {
            "@id": "http://enpaku-jdta.jp/api/items/217023",
            "display_title": "原金太郎",
            "is_public": true,
            "property_id": 486,
            "property_label": "出演者",
            "type": "resource",
            "url": null,
            "value_resource_id": 217023,
            "value_resource_name": "items"
        },
        {
            "@id": "http://enpaku-jdta.jp/api/items/217024",
            "display_title": "坂田聡",
            "is_public": true,
            "property_id": 486,
            "property_label": "出演者",
            "type": "resource",
            "url": null,
            "value_resource_id": 217024,
            "value_resource_name": "items"
        },
        {
            "@id": "http://enpaku-jdta.jp/api/items/217025",
            "display_title": "池谷のぶえ",
            "is_public": true,
            "property_id": 486,
            "property_label": "出演者",
            "type": "resource",
            "url": null,
            "value_resource_id": 217025,
            "value_resource_name": "items"
        },
        {
            "@id": "http://enpaku-jdta.jp/api/items/217026",
            "display_title": "加藤啓",
            "is_public": true,
            "property_id": 486,
            "property_label": "出演者",
            "type": "resource",
            "url": null,
            "value_resource_id": 217026,
            "value_resource_name": "items"
        },
        {
            "@id": "http://enpaku-jdta.jp/api/items/217027",
            "display_title": "立石涼子",
            "is_public": true,
            "property_id": 486,
            "property_label": "出演者",
            "type": "resource",
            "url": null,
            "value_resource_id": 217027,
            "value_resource_name": "items"
        },
        {
            "@id": "http://enpaku-jdta.jp/api/items/217028",
            "display_title": "松野有里巳",
            "is_public": true,
            "property_id": 486,
            "property_label": "出演者",
            "type": "resource",
            "url": null,
            "value_resource_id": 217028,
            "value_resource_name": "items"
        },
        {
            "@id": "http://enpaku-jdta.jp/api/items/217029",
            "display_title": "秋山菜津子",
            "is_public": true,
            "property_id": 486,
            "property_label": "出演者",
            "type": "resource",
            "url": null,
            "value_resource_id": 217029,
            "value_resource_name": "items"
        }
    ],
    "dcepk:sourceIdentifier": [
        {
            "@value": "02367-01-2006-08:1-1",
            "is_public": true,
            "property_id": 516,
            "property_label": "ソースID",
            "type": "literal"
        }
    ],
    "dcepk:titleTranscription": [
        {
            "@language": "ja",
            "@value": "ないすえいじ",
            "is_public": true,
            "property_id": 517,
            "property_label": "公演名よみ",
            "type": "literal"
        }
    ],
    "dcterms:contributor": [
        {
            "@id": "http://enpaku-jdta.jp/api/items/227695",
            "display_title": "ケラリーノ・サンドロヴィッチ",
            "is_public": true,
            "property_id": 6,
            "property_label": "Contributor",
            "type": "resource",
            "url": null,
            "value_resource_id": 227695,
            "value_resource_name": "items"
        },
        {
            "@id": "http://enpaku-jdta.jp/api/items/227696",
            "display_title": "ケラリーノ・サンドロヴィッチ",
            "is_public": true,
            "property_id": 6,
            "property_label": "Contributor",
            "type": "resource",
            "url": null,
            "value_resource_id": 227696,
            "value_resource_name": "items"
        },
        {
            "@id": "http://enpaku-jdta.jp/api/items/227697",
            "display_title": "水越佳一",
            "is_public": true,
            "property_id": 6,
            "property_label": "Contributor",
            "type": "resource",
            "url": null,
            "value_resource_id": 227697,
            "value_resource_name": "items"
        },
        {
            "@id": "http://enpaku-jdta.jp/api/items/227698",
            "display_title": "関口裕二",
            "is_public": true,
            "property_id": 6,
            "property_label": "Contributor",
            "type": "resource",
            "url": null,
            "value_resource_id": 227698,
            "value_resource_name": "items"
        },
        {
            "@id": "http://enpaku-jdta.jp/api/items/227699",
            "display_title": "上田大樹",
            "is_public": true,
            "property_id": 6,
            "property_label": "Contributor",
            "type": "resource",
            "url": null,
            "value_resource_id": 227699,
            "value_resource_name": "items"
        },
        {
            "@id": "http://enpaku-jdta.jp/api/items/227700",
            "display_title": "三大寺志保美",
            "is_public": true,
            "property_id": 6,
            "property_label": "Contributor",
            "type": "resource",
            "url": null,
            "value_resource_id": 227700,
            "value_resource_name": "items"
        },
        {
            "@id": "http://enpaku-jdta.jp/api/items/227701",
            "display_title": "武井優子",
            "is_public": true,
            "property_id": 6,
            "property_label": "Contributor",
            "type": "resource",
            "url": null,
            "value_resource_id": 227701,
            "value_resource_name": "items"
        },
        {
            "@id": "http://enpaku-jdta.jp/api/items/227702",
            "display_title": "長田奈麻",
            "is_public": true,
            "property_id": 6,
            "property_label": "Contributor",
            "type": "resource",
            "url": null,
            "value_resource_id": 227702,
            "value_resource_name": "items"
        }
    ],
    "dcterms:identifier": [
        {
            "@value": "pg-0d2c4d8504f7180e8d3eb9d671e18e6f",
            "is_public": true,
            "property_id": 10,
            "property_label": "Identifier",
            "type": "literal"
        },
        {
            "@value": "pg-0d2c4d8504f7180e8d3eb9d671e18e6f",
            "is_public": true,
            "property_id": 10,
            "property_label": "Identifier",
            "type": "literal"
        }
    ],
    "dcterms:title": [
        {
            "@language": "ja",
            "@value": "ナイス・エイジ",
            "is_public": true,
            "property_id": 1,
            "property_label": "Title",
            "type": "literal"
        },
        {
            "@language": "en",
            "@value": "Nice Age",
            "is_public": true,
            "property_id": 1,
            "property_label": "Title",
            "type": "literal"
        }
    ],
    "dcterms:type": [
        {
            "@value": "http://purl.org/dc/dcmitype/MovingImage",
            "is_public": true,
            "property_id": 8,
            "property_label": "Type",
            "type": "literal"
        }
    ],
    "o:created": {
        "@type": "http://www.w3.org/2001/XMLSchema#dateTime",
        "@value": "2021-02-19T12:19:01+00:00"
    },
    "o:id": 234791,
    "o:is_public": true,
    "o:item_set": [],
    "o:media": [],
    "o:modified": {
        "@type": "http://www.w3.org/2001/XMLSchema#dateTime",
        "@value": "2021-02-20T04:22:38+00:00"
    },
    "o:owner": {
        "@id": "http://enpaku-jdta.jp/api/users/1",
        "o:id": 1
    },
    "o:resource_class": null,
    "o:resource_template": {
        "@id": "http://enpaku-jdta.jp/api/resource_templates/10",
        "o:id": 10
    },
    "o:site": [
        {
            "@id": "http://enpaku-jdta.jp/api/sites/1",
            "o:id": 1
        }
    ],
    "o:thumbnail": null,
    "o:title": "ナイス・エイジ",
    "thumbnail_display_urls": {
        "large": null,
        "medium": null,
        "square": null
    }
}