{
    "@context": "http://enpaku-jdta.jp/api-context",
    "@id": "http://enpaku-jdta.jp/api/items/235429",
    "@type": "o:Item",
    "dcepk:actor": [
        {
            "@id": "http://enpaku-jdta.jp/api/items/220200",
            "display_title": "安藤玉恵",
            "is_public": true,
            "property_id": 486,
            "property_label": "出演者",
            "type": "resource",
            "url": null,
            "value_resource_id": 220200,
            "value_resource_name": "items"
        },
        {
            "@id": "http://enpaku-jdta.jp/api/items/220201",
            "display_title": "福本雄樹",
            "is_public": true,
            "property_id": 486,
            "property_label": "出演者",
            "type": "resource",
            "url": null,
            "value_resource_id": 220201,
            "value_resource_name": "items"
        },
        {
            "@id": "http://enpaku-jdta.jp/api/items/220202",
            "display_title": "山岸門人",
            "is_public": true,
            "property_id": 486,
            "property_label": "出演者",
            "type": "resource",
            "url": null,
            "value_resource_id": 220202,
            "value_resource_name": "items"
        },
        {
            "@id": "http://enpaku-jdta.jp/api/items/220203",
            "display_title": "浅井智佳子",
            "is_public": true,
            "property_id": 486,
            "property_label": "出演者",
            "type": "resource",
            "url": null,
            "value_resource_id": 220203,
            "value_resource_name": "items"
        }
    ],
    "dcepk:sourceIdentifier": [
        {
            "@value": "10159-01-2017-01:1-1",
            "is_public": true,
            "property_id": 516,
            "property_label": "ソースID",
            "type": "literal"
        }
    ],
    "dcepk:titleTranscription": [
        {
            "@language": "ja",
            "@value": "だんじょぎゃくてんばんちじんのあい",
            "is_public": true,
            "property_id": 517,
            "property_label": "公演名よみ",
            "type": "literal"
        }
    ],
    "dcterms:contributor": [
        {
            "@id": "http://enpaku-jdta.jp/api/items/231589",
            "display_title": "谷崎潤一郎",
            "is_public": true,
            "property_id": 6,
            "property_label": "Contributor",
            "type": "resource",
            "url": null,
            "value_resource_id": 231589,
            "value_resource_name": "items"
        },
        {
            "@id": "http://enpaku-jdta.jp/api/items/231590",
            "display_title": "ペヤンヌマキ",
            "is_public": true,
            "property_id": 6,
            "property_label": "Contributor",
            "type": "resource",
            "url": null,
            "value_resource_id": 231590,
            "value_resource_name": "items"
        },
        {
            "@id": "http://enpaku-jdta.jp/api/items/231591",
            "display_title": "ペヤンヌマキ",
            "is_public": true,
            "property_id": 6,
            "property_label": "Contributor",
            "type": "resource",
            "url": null,
            "value_resource_id": 231591,
            "value_resource_name": "items"
        },
        {
            "@id": "http://enpaku-jdta.jp/api/items/231592",
            "display_title": "田中敏恵",
            "is_public": true,
            "property_id": 6,
            "property_label": "Contributor",
            "type": "resource",
            "url": null,
            "value_resource_id": 231592,
            "value_resource_name": "items"
        },
        {
            "@id": "http://enpaku-jdta.jp/api/items/231593",
            "display_title": "伊藤孝",
            "is_public": true,
            "property_id": 6,
            "property_label": "Contributor",
            "type": "resource",
            "url": null,
            "value_resource_id": 231593,
            "value_resource_name": "items"
        },
        {
            "@id": "http://enpaku-jdta.jp/api/items/231594",
            "display_title": "中村嘉宏",
            "is_public": true,
            "property_id": 6,
            "property_label": "Contributor",
            "type": "resource",
            "url": null,
            "value_resource_id": 231594,
            "value_resource_name": "items"
        }
    ],
    "dcterms:identifier": [
        {
            "@value": "pg-67e482fc05db7a4902060112d232b77b",
            "is_public": true,
            "property_id": 10,
            "property_label": "Identifier",
            "type": "literal"
        },
        {
            "@value": "pg-67e482fc05db7a4902060112d232b77b",
            "is_public": true,
            "property_id": 10,
            "property_label": "Identifier",
            "type": "literal"
        }
    ],
    "dcterms:title": [
        {
            "@language": "ja",
            "@value": "男女逆転版・痴人の愛",
            "is_public": true,
            "property_id": 1,
            "property_label": "Title",
            "type": "literal"
        },
        {
            "@language": "en",
            "@value": "Gender-Flipped Version - Naomi",
            "is_public": true,
            "property_id": 1,
            "property_label": "Title",
            "type": "literal"
        }
    ],
    "dcterms:type": [
        {
            "@value": "http://purl.org/dc/dcmitype/MovingImage",
            "is_public": true,
            "property_id": 8,
            "property_label": "Type",
            "type": "literal"
        }
    ],
    "o:created": {
        "@type": "http://www.w3.org/2001/XMLSchema#dateTime",
        "@value": "2021-02-19T12:19:27+00:00"
    },
    "o:id": 235429,
    "o:is_public": true,
    "o:item_set": [],
    "o:media": [],
    "o:modified": {
        "@type": "http://www.w3.org/2001/XMLSchema#dateTime",
        "@value": "2021-02-20T04:23:18+00:00"
    },
    "o:owner": {
        "@id": "http://enpaku-jdta.jp/api/users/1",
        "o:id": 1
    },
    "o:resource_class": null,
    "o:resource_template": {
        "@id": "http://enpaku-jdta.jp/api/resource_templates/10",
        "o:id": 10
    },
    "o:site": [
        {
            "@id": "http://enpaku-jdta.jp/api/sites/1",
            "o:id": 1
        }
    ],
    "o:thumbnail": null,
    "o:title": "男女逆転版・痴人の愛",
    "thumbnail_display_urls": {
        "large": null,
        "medium": null,
        "square": null
    }
}