{
    "@context": "http://enpaku-jdta.jp/api-context",
    "@id": "http://enpaku-jdta.jp/api/items/237849",
    "@type": [
        "o:Item",
        "dcepk:TheatricalResource"
    ],
    "dcepk:applicantAgent": [
        {
            "@id": "http://enpaku-jdta.jp/api/items/207733",
            "display_title": "地点",
            "is_public": true,
            "property_id": 488,
            "property_label": "公演情報提供者",
            "type": "resource",
            "url": null,
            "value_resource_id": 207733,
            "value_resource_name": "items"
        }
    ],
    "dcepk:creatorNameforDisplay": [
        {
            "@language": "ja",
            "@value": "三浦基",
            "is_public": true,
            "property_id": 520,
            "property_label": "一覧表示用　演出家・振付家名",
            "type": "literal"
        },
        {
            "@language": "en",
            "@value": "MIURA Motoi",
            "is_public": true,
            "property_id": 520,
            "property_label": "一覧表示用　演出家・振付家名",
            "type": "literal"
        }
    ],
    "dcepk:dateClosing": [
        {
            "@value": "2020/12/6",
            "is_public": true,
            "property_id": 494,
            "property_label": "公演終了日",
            "type": "literal"
        }
    ],
    "dcepk:descriptionAboutPerformance": [
        {
            "@language": "ja",
            "@value": "Chiten, Keep Your Front Up英訳あり（あらすじ・上演主体代表者名）",
            "is_public": true,
            "property_id": 495,
            "property_label": "記載事項(情報提供者から)",
            "type": "literal"
        }
    ],
    "dcepk:epadCategory": [
        {
            "@language": "ja",
            "@value": "演劇",
            "is_public": true,
            "property_id": 497,
            "property_label": "EPAD分野",
            "type": "literal"
        },
        {
            "@language": "en",
            "@value": "Contemporary Theatre",
            "is_public": true,
            "property_id": 497,
            "property_label": "EPAD分野",
            "type": "literal"
        }
    ],
    "dcepk:epadRequestNo": [
        {
            "@value": "P01024",
            "is_public": true,
            "property_id": 498,
            "property_label": "EPAD事業受付番号",
            "type": "literal"
        }
    ],
    "dcepk:performanceVenue": [
        {
            "@language": "ja",
            "@value": "アンダースロー",
            "is_public": true,
            "property_id": 509,
            "property_label": "会場",
            "type": "literal"
        },
        {
            "@language": "en",
            "@value": "ANDASURO",
            "is_public": true,
            "property_id": 509,
            "property_label": "会場",
            "type": "literal"
        }
    ],
    "dcepk:performanceVenueTranscription": [
        {
            "@language": "ja",
            "@value": "あんだーすろー",
            "is_public": true,
            "property_id": 510,
            "property_label": "会場よみ",
            "type": "literal"
        }
    ],
    "dcepk:programme": [
        {
            "@id": "http://enpaku-jdta.jp/api/items/234437",
            "display_title": "正面に気をつけろ",
            "is_public": true,
            "property_id": 512,
            "property_label": "上演作品情報",
            "type": "resource",
            "url": null,
            "value_resource_id": 234437,
            "value_resource_name": "items"
        }
    ],
    "dcepk:relatedItem": [
        {
            "@id": "http://enpaku-jdta.jp/api/items/234398",
            "display_title": "EV00216678",
            "is_public": true,
            "property_id": 513,
            "property_label": "関連資料",
            "thumbnail_title": "EV00216678_thum01.jpg",
            "thumbnail_type": "image/jpeg",
            "thumbnail_url": "/files/square/aaa75ba9de86b2989c96a87be293b033f7a6be2b.jpg",
            "type": "resource",
            "url": null,
            "value_resource_id": 234398,
            "value_resource_name": "items"
        }
    ],
    "dcepk:relatedStillImage": [
        {
            "@id": "http://enpaku-jdta.jp/api/items/235660",
            "display_title": "01_08223-01-2020-03_01.jpg.jpg",
            "is_public": true,
            "property_id": 519,
            "property_label": "relatedStillImage",
            "thumbnail_title": "08223-01-2020-03_01.jpg",
            "thumbnail_type": "image/jpeg",
            "thumbnail_url": "/files/square/fe0a718ede75c178f2317142cf8ae138e57d0d5d.jpg",
            "type": "resource",
            "url": null,
            "value_resource_id": 235660,
            "value_resource_name": "items"
        },
        {
            "@id": "http://enpaku-jdta.jp/api/items/235661",
            "display_title": "02_08223-01-2020-03_02.jpg.jpg",
            "is_public": true,
            "property_id": 519,
            "property_label": "relatedStillImage",
            "thumbnail_title": "08223-01-2020-03_02.jpg",
            "thumbnail_type": "image/jpeg",
            "thumbnail_url": "/files/square/be48b0a5a141d4599e17e97d51951d8487589f66.jpg",
            "type": "resource",
            "url": null,
            "value_resource_id": 235661,
            "value_resource_name": "items"
        },
        {
            "@id": "http://enpaku-jdta.jp/api/items/235662",
            "display_title": "03_08223-01-2020-03_03.jpg.jpg",
            "is_public": true,
            "property_id": 519,
            "property_label": "relatedStillImage",
            "thumbnail_title": "08223-01-2020-03_03.jpg",
            "thumbnail_type": "image/jpeg",
            "thumbnail_url": "/files/square/0a028c328d47641720352fcc77f4a0fbb3ad1888.jpg",
            "type": "resource",
            "url": null,
            "value_resource_id": 235662,
            "value_resource_name": "items"
        }
    ],
    "dcepk:sourceIdentifier": [
        {
            "@value": "08223-01-2020-03",
            "is_public": true,
            "property_id": 516,
            "property_label": "ソースID",
            "type": "literal"
        }
    ],
    "dcepk:titleTranscription": [
        {
            "@language": "ja",
            "@value": "しょうめんにきをつけろ",
            "is_public": true,
            "property_id": 517,
            "property_label": "公演名よみ",
            "type": "literal"
        }
    ],
    "dcterms:abstract": [
        {
            "@language": "ja",
            "@value": "作者・松原俊太郎が演劇と出会うきっかけとなったブレヒト作『ファッツァー』をモチーフに、第一次世界大戦中の脱走兵を戦後日本に甦った英霊にトレース。「やってきた者たち」として戦争と自らの生死について語る彼らは、ときに閉塞感に悩む日本人の現在の姿を彷彿とさせ、さらには波にさらわれた記憶を語るなど、多くの人々の生きていた時間を一身に引き受けた、どこの誰とも特定できない存在だ。反復を恐れず、たわむことのない思考は、その場に居合わせた人々になにをもたらすのか。",
            "is_public": true,
            "property_id": 19,
            "property_label": "Abstract",
            "type": "literal"
        },
        {
            "@language": "en",
            "@value": "The characters on stage are the spirits of the war dead. These visitors, who talk of war and their lives and deaths, seem to have come from the past, while they also may represent an image of the Japanese today, troubled by stagnation. At the same time, these figures do not appear specific to any one place, but rather have taken on the weight of the experiences of so many, relating their memories washed away by the waves. They endeavor to break free from a state where being alive and being dead are one and the same, or from the relationship between controlling and controlled. What will their ideas that never slack, unfazed by repetition, offer to those others who come to that place? This performance unfolds as a contest between their voices and sounds created by live music from alternative rock band kukangendai.",
            "is_public": true,
            "property_id": 19,
            "property_label": "Abstract",
            "type": "literal"
        }
    ],
    "dcterms:date": [
        {
            "@value": "2020",
            "is_public": true,
            "property_id": 7,
            "property_label": "Date",
            "type": "literal"
        }
    ],
    "dcterms:identifier": [
        {
            "@value": "08223-01-2020-03",
            "is_public": true,
            "property_id": 10,
            "property_label": "Identifier",
            "type": "literal"
        },
        {
            "@value": "08223-01-2020-03",
            "is_public": true,
            "property_id": 10,
            "property_label": "Identifier",
            "type": "literal"
        }
    ],
    "dcterms:subject": [
        {
            "@language": "ja",
            "@value": "現代劇",
            "is_public": true,
            "property_id": 3,
            "property_label": "Subject",
            "type": "literal"
        },
        {
            "@language": "ja",
            "@value": "音楽劇",
            "is_public": true,
            "property_id": 3,
            "property_label": "Subject",
            "type": "literal"
        },
        {
            "@language": "en",
            "@value": "contemporary theater",
            "is_public": true,
            "property_id": 3,
            "property_label": "Subject",
            "type": "literal"
        },
        {
            "@language": "en",
            "@value": "music show",
            "is_public": true,
            "property_id": 3,
            "property_label": "Subject",
            "type": "literal"
        }
    ],
    "dcterms:temporal": [
        {
            "@value": "2020/12/4",
            "is_public": true,
            "property_id": 41,
            "property_label": "Temporal Coverage",
            "type": "literal"
        }
    ],
    "dcterms:title": [
        {
            "@language": "ja",
            "@value": "正面に気をつけろ",
            "is_public": true,
            "property_id": 1,
            "property_label": "Title",
            "type": "literal"
        },
        {
            "@language": "en",
            "@value": "Keep Your Front Up",
            "is_public": true,
            "property_id": 1,
            "property_label": "Title",
            "type": "literal"
        }
    ],
    "dcterms:type": [
        {
            "@value": "http://purl.org/dc/dcmitype/Event",
            "is_public": true,
            "property_id": 8,
            "property_label": "Type",
            "type": "literal"
        }
    ],
    "o:created": {
        "@type": "http://www.w3.org/2001/XMLSchema#dateTime",
        "@value": "2021-02-19T12:26:57+00:00"
    },
    "o:id": 237849,
    "o:is_public": true,
    "o:item_set": [],
    "o:media": [],
    "o:modified": {
        "@type": "http://www.w3.org/2001/XMLSchema#dateTime",
        "@value": "2021-02-19T13:56:23+00:00"
    },
    "o:owner": {
        "@id": "http://enpaku-jdta.jp/api/users/1",
        "o:id": 1
    },
    "o:resource_class": {
        "@id": "http://enpaku-jdta.jp/api/resource_classes/306",
        "o:id": 306
    },
    "o:resource_template": {
        "@id": "http://enpaku-jdta.jp/api/resource_templates/2",
        "o:id": 2
    },
    "o:site": [
        {
            "@id": "http://enpaku-jdta.jp/api/sites/1",
            "o:id": 1
        }
    ],
    "o:thumbnail": null,
    "o:title": "正面に気をつけろ",
    "thumbnail_display_urls": {
        "large": null,
        "medium": null,
        "square": null
    }
}