{
    "@context": "http://enpaku-jdta.jp/api-context",
    "@id": "http://enpaku-jdta.jp/api/items/238346",
    "@type": [
        "o:Item",
        "dcepk:TheatricalResource"
    ],
    "dcepk:applicantAgent": [
        {
            "@id": "http://enpaku-jdta.jp/api/items/208230",
            "display_title": "一般社団法人演劇集団ワンダーランド",
            "is_public": true,
            "property_id": 488,
            "property_label": "公演情報提供者",
            "type": "resource",
            "url": null,
            "value_resource_id": 208230,
            "value_resource_name": "items"
        }
    ],
    "dcepk:creatorNameforDisplay": [
        {
            "@language": "ja",
            "@value": "竹内一郎",
            "is_public": true,
            "property_id": 520,
            "property_label": "一覧表示用　演出家・振付家名",
            "type": "literal"
        },
        {
            "@language": "en",
            "@value": "TAKEUCHI Ichirou",
            "is_public": true,
            "property_id": 520,
            "property_label": "一覧表示用　演出家・振付家名",
            "type": "literal"
        }
    ],
    "dcepk:dateClosing": [
        {
            "@value": "2011/5/29",
            "is_public": true,
            "property_id": 494,
            "property_label": "公演終了日",
            "type": "literal"
        }
    ],
    "dcepk:epadCategory": [
        {
            "@language": "ja",
            "@value": "演劇",
            "is_public": true,
            "property_id": 497,
            "property_label": "EPAD分野",
            "type": "literal"
        },
        {
            "@language": "en",
            "@value": "Contemporary Theatre",
            "is_public": true,
            "property_id": 497,
            "property_label": "EPAD分野",
            "type": "literal"
        }
    ],
    "dcepk:epadRequestNo": [
        {
            "@value": "P01874",
            "is_public": true,
            "property_id": 498,
            "property_label": "EPAD事業受付番号",
            "type": "literal"
        }
    ],
    "dcepk:keywordbyApplicantAgent": [
        {
            "@language": "ja",
            "@value": "評伝劇",
            "is_public": true,
            "property_id": 501,
            "property_label": "キーワード(提供者作成)",
            "type": "literal"
        },
        {
            "@language": "en",
            "@value": "biography",
            "is_public": true,
            "property_id": 501,
            "property_label": "キーワード(提供者作成)",
            "type": "literal"
        }
    ],
    "dcepk:performanceVenue": [
        {
            "@language": "ja",
            "@value": "紀伊國屋ホール（新宿）",
            "is_public": true,
            "property_id": 509,
            "property_label": "会場",
            "type": "literal"
        },
        {
            "@language": "en",
            "@value": "KINOKUNIYAHORU",
            "is_public": true,
            "property_id": 509,
            "property_label": "会場",
            "type": "literal"
        }
    ],
    "dcepk:performanceVenueTranscription": [
        {
            "@language": "ja",
            "@value": "きのくにやほーる",
            "is_public": true,
            "property_id": 510,
            "property_label": "会場よみ",
            "type": "literal"
        }
    ],
    "dcepk:programme": [
        {
            "@id": "http://enpaku-jdta.jp/api/items/234964",
            "display_title": "からくり儀右衛門　東芝を創った男",
            "is_public": true,
            "property_id": 512,
            "property_label": "上演作品情報",
            "type": "resource",
            "url": null,
            "value_resource_id": 234964,
            "value_resource_name": "items"
        }
    ],
    "dcepk:relatedItem": [
        {
            "@id": "http://enpaku-jdta.jp/api/items/233411",
            "display_title": "EV00215306",
            "is_public": true,
            "property_id": 513,
            "property_label": "関連資料",
            "thumbnail_title": "EV00215306_thum01.jpg",
            "thumbnail_type": "image/jpeg",
            "thumbnail_url": "/files/square/72dfe76e0e7ac8e165df3d939a1575b92523aaa4.jpg",
            "type": "resource",
            "url": null,
            "value_resource_id": 233411,
            "value_resource_name": "items"
        },
        {
            "@id": "http://enpaku-jdta.jp/api/items/233412",
            "display_title": "EV00215307",
            "is_public": true,
            "property_id": 513,
            "property_label": "関連資料",
            "thumbnail_title": "EV00215307_thum01.jpg",
            "thumbnail_type": "image/jpeg",
            "thumbnail_url": "/files/square/6ee4f6d34f8b2694dd7bc9230a3e5d85ca14aff9.jpg",
            "type": "resource",
            "url": null,
            "value_resource_id": 233412,
            "value_resource_name": "items"
        }
    ],
    "dcepk:relatedStillImage": [
        {
            "@id": "http://enpaku-jdta.jp/api/items/236733",
            "display_title": "01_00524-01-2011-01_01.jpg.jpg",
            "is_public": true,
            "property_id": 519,
            "property_label": "relatedStillImage",
            "thumbnail_title": "00524-01-2011-01_01.jpg",
            "thumbnail_type": "image/jpeg",
            "thumbnail_url": "/files/square/fc44475d6e3c3adcfc8ad62538fbeb78561e1877.jpg",
            "type": "resource",
            "url": null,
            "value_resource_id": 236733,
            "value_resource_name": "items"
        }
    ],
    "dcepk:sourceIdentifier": [
        {
            "@value": "00524-01-2011-01",
            "is_public": true,
            "property_id": 516,
            "property_label": "ソースID",
            "type": "literal"
        }
    ],
    "dcepk:titleTranscription": [
        {
            "@language": "ja",
            "@value": "からくりぎえもん　とうしばをつくったおとこ",
            "is_public": true,
            "property_id": 517,
            "property_label": "公演名よみ",
            "type": "literal"
        }
    ],
    "dcterms:abstract": [
        {
            "@language": "ja",
            "@value": "江戸末期――。田中儀右衛門は、十代前半で既に地元・久留米で「からくり師」として注目を集めていた。彼が、久留米がすりの創始者・井上伝の求めに応じ、花や蝶などの洒落た柄を織り込む技法を開発し、地元産業の発展に貢献したのが十五歳のときだった。発明の面白さに魅了された儀右衛門は、からくり人形を見せる見世物小屋の興行師として大阪で活躍する。その後、大塩平八郎と出会い、〈仕事の使命〉に開眼する儀右衛門。だが、その出会いは儀右衛門の運命を大きく変えていく…。佐賀藩、久留米藩に戻り、蒸気機関、アームストロング砲などの開発に携わり、技術で明治維新に貢献する。明治以降は政府の要請に応え、西洋技術の国産化を推進し、東芝の前身をつくるに至る、田中儀右衛門の生き様を描く。\r\n 作品は実話を基にしたフィクションです。",
            "is_public": true,
            "property_id": 19,
            "property_label": "Abstract",
            "type": "literal"
        },
        {
            "@language": "en",
            "@value": "Late Edo Period. Tanaka Giemon was already attracting attention as a “Karakuri” (mechanical dolls) master in his hometown of Kurume in his early teenage years. He was 15 years old when he developed techniques that incorporate stylish patterns such as flowers and butterflies at the request of Inoue Den, who was the founder of the Kurume Kasuri fabric technique, and contributed to the local industry. Giemon, who was fascinated by the joys of invention, becomes active in Osaka as a showman in a show booth that displays karakuri figures. \r\nAfterwards, Giemon meets Oshio Heihachiro and opens his eyes to the “calling of work”. However, this encounters greatly changes the course of Giemon’s life…he returns to the Saga and Kurume domains and was involved in the development of steam engines and Armstrong guns, contributing technology to the Meiji Restoration. Depicted here is the life of Tanaka Giemon, a man who promoted domestic production of Western technology in response to the government’s request in the Meiji era, and created the predecessor of Toshiba. \r\nThis work is a fiction based on a true story.",
            "is_public": true,
            "property_id": 19,
            "property_label": "Abstract",
            "type": "literal"
        }
    ],
    "dcterms:date": [
        {
            "@value": "2011",
            "is_public": true,
            "property_id": 7,
            "property_label": "Date",
            "type": "literal"
        }
    ],
    "dcterms:identifier": [
        {
            "@value": "00524-01-2011-01",
            "is_public": true,
            "property_id": 10,
            "property_label": "Identifier",
            "type": "literal"
        },
        {
            "@value": "00524-01-2011-01",
            "is_public": true,
            "property_id": 10,
            "property_label": "Identifier",
            "type": "literal"
        }
    ],
    "dcterms:subject": [
        {
            "@language": "ja",
            "@value": "現代劇",
            "is_public": true,
            "property_id": 3,
            "property_label": "Subject",
            "type": "literal"
        },
        {
            "@language": "en",
            "@value": "contemporary theater",
            "is_public": true,
            "property_id": 3,
            "property_label": "Subject",
            "type": "literal"
        }
    ],
    "dcterms:temporal": [
        {
            "@value": "2011/5/26",
            "is_public": true,
            "property_id": 41,
            "property_label": "Temporal Coverage",
            "type": "literal"
        }
    ],
    "dcterms:title": [
        {
            "@language": "ja",
            "@value": "からくり儀右衛門　東芝を創った男",
            "is_public": true,
            "property_id": 1,
            "property_label": "Title",
            "type": "literal"
        },
        {
            "@language": "en",
            "@value": "Karakurigiemon　Toshibaotsukuttaotoko",
            "is_public": true,
            "property_id": 1,
            "property_label": "Title",
            "type": "literal"
        }
    ],
    "dcterms:type": [
        {
            "@value": "http://purl.org/dc/dcmitype/Event",
            "is_public": true,
            "property_id": 8,
            "property_label": "Type",
            "type": "literal"
        }
    ],
    "o:created": {
        "@type": "http://www.w3.org/2001/XMLSchema#dateTime",
        "@value": "2021-02-19T12:27:09+00:00"
    },
    "o:id": 238346,
    "o:is_public": true,
    "o:item_set": [],
    "o:media": [],
    "o:modified": {
        "@type": "http://www.w3.org/2001/XMLSchema#dateTime",
        "@value": "2021-02-19T13:56:27+00:00"
    },
    "o:owner": {
        "@id": "http://enpaku-jdta.jp/api/users/1",
        "o:id": 1
    },
    "o:resource_class": {
        "@id": "http://enpaku-jdta.jp/api/resource_classes/306",
        "o:id": 306
    },
    "o:resource_template": {
        "@id": "http://enpaku-jdta.jp/api/resource_templates/2",
        "o:id": 2
    },
    "o:site": [
        {
            "@id": "http://enpaku-jdta.jp/api/sites/1",
            "o:id": 1
        }
    ],
    "o:thumbnail": null,
    "o:title": "からくり儀右衛門　東芝を創った男",
    "thumbnail_display_urls": {
        "large": null,
        "medium": null,
        "square": null
    }
}