{
    "@context": "http://enpaku-jdta.jp/api-context",
    "@id": "http://enpaku-jdta.jp/api/items/238609",
    "@type": [
        "o:Item",
        "dcepk:TheatricalResource"
    ],
    "dcepk:applicantAgent": [
        {
            "@id": "http://enpaku-jdta.jp/api/items/208493",
            "display_title": "BATIK",
            "is_public": true,
            "property_id": 488,
            "property_label": "公演情報提供者",
            "type": "resource",
            "url": null,
            "value_resource_id": 208493,
            "value_resource_name": "items"
        }
    ],
    "dcepk:creatorNameforDisplay": [
        {
            "@language": "ja",
            "@value": "黒田育世",
            "is_public": true,
            "property_id": 520,
            "property_label": "一覧表示用　演出家・振付家名",
            "type": "literal"
        },
        {
            "@language": "en",
            "@value": "KURODA Ikuyo",
            "is_public": true,
            "property_id": 520,
            "property_label": "一覧表示用　演出家・振付家名",
            "type": "literal"
        }
    ],
    "dcepk:dateClosing": [
        {
            "@value": "2200/3/31",
            "is_public": true,
            "property_id": 494,
            "property_label": "公演終了日",
            "type": "literal"
        }
    ],
    "dcepk:epadCategory": [
        {
            "@language": "ja",
            "@value": "舞踊",
            "is_public": true,
            "property_id": 497,
            "property_label": "EPAD分野",
            "type": "literal"
        },
        {
            "@language": "en",
            "@value": "Dance",
            "is_public": true,
            "property_id": 497,
            "property_label": "EPAD分野",
            "type": "literal"
        }
    ],
    "dcepk:epadRequestNo": [
        {
            "@value": "P02268",
            "is_public": true,
            "property_id": 498,
            "property_label": "EPAD事業受付番号",
            "type": "literal"
        }
    ],
    "dcepk:keywordbyApplicantAgent": [
        {
            "@language": "en",
            "@value": "Ends in the dark",
            "is_public": true,
            "property_id": 501,
            "property_label": "キーワード(提供者作成)",
            "type": "literal"
        },
        {
            "@language": "en",
            "@value": "Proscenium",
            "is_public": true,
            "property_id": 501,
            "property_label": "キーワード(提供者作成)",
            "type": "literal"
        },
        {
            "@language": "en",
            "@value": "With music",
            "is_public": true,
            "property_id": 501,
            "property_label": "キーワード(提供者作成)",
            "type": "literal"
        },
        {
            "@language": "en",
            "@value": "songs",
            "is_public": true,
            "property_id": 501,
            "property_label": "キーワード(提供者作成)",
            "type": "literal"
        }
    ],
    "dcepk:keywordbyEpadOffice": [
        {
            "@language": "ja",
            "@value": "暗転で終わる",
            "is_public": true,
            "property_id": 502,
            "property_label": "キーワード(手動作成)",
            "type": "literal"
        },
        {
            "@language": "ja",
            "@value": "プロセニアム",
            "is_public": true,
            "property_id": 502,
            "property_label": "キーワード(手動作成)",
            "type": "literal"
        },
        {
            "@language": "ja",
            "@value": "音楽あり",
            "is_public": true,
            "property_id": 502,
            "property_label": "キーワード(手動作成)",
            "type": "literal"
        },
        {
            "@language": "ja",
            "@value": "歌あり",
            "is_public": true,
            "property_id": 502,
            "property_label": "キーワード(手動作成)",
            "type": "literal"
        }
    ],
    "dcepk:performanceVenue": [
        {
            "@language": "ja",
            "@value": "世田谷パブリックシアター",
            "is_public": true,
            "property_id": 509,
            "property_label": "会場",
            "type": "literal"
        },
        {
            "@language": "en",
            "@value": "Setagaya Public Thatre",
            "is_public": true,
            "property_id": 509,
            "property_label": "会場",
            "type": "literal"
        }
    ],
    "dcepk:performanceVenueTranscription": [
        {
            "@language": "ja",
            "@value": "せたがやぱぶりっくしあたー",
            "is_public": true,
            "property_id": 510,
            "property_label": "会場よみ",
            "type": "literal"
        }
    ],
    "dcepk:programme": [
        {
            "@id": "http://enpaku-jdta.jp/api/items/235227",
            "display_title": "ペンダント・イヴ",
            "is_public": true,
            "property_id": 512,
            "property_label": "上演作品情報",
            "type": "resource",
            "url": null,
            "value_resource_id": 235227,
            "value_resource_name": "items"
        }
    ],
    "dcepk:relatedItem": [
        {
            "@id": "http://enpaku-jdta.jp/api/items/233794",
            "display_title": "EV00215784",
            "is_public": true,
            "property_id": 513,
            "property_label": "関連資料",
            "thumbnail_title": "EV00215784_thum01.jpg",
            "thumbnail_type": "image/jpeg",
            "thumbnail_url": "/files/square/5678f5b9ef756e9f341c42cbe55557527705fd07.jpg",
            "type": "resource",
            "url": null,
            "value_resource_id": 233794,
            "value_resource_name": "items"
        }
    ],
    "dcepk:relatedStillImage": [
        {
            "@id": "http://enpaku-jdta.jp/api/items/237148",
            "display_title": "01_09274-01-2007-02_01.jpg.jpg",
            "is_public": true,
            "property_id": 519,
            "property_label": "relatedStillImage",
            "thumbnail_title": "09274-01-2007-02_01.jpg",
            "thumbnail_type": "image/jpeg",
            "thumbnail_url": "/files/square/d41ab1ab952b50b2813186bff0ae622f5444ced1.jpg",
            "type": "resource",
            "url": null,
            "value_resource_id": 237148,
            "value_resource_name": "items"
        },
        {
            "@id": "http://enpaku-jdta.jp/api/items/237149",
            "display_title": "02_09274-01-2007-02_02.jpg.jpg",
            "is_public": true,
            "property_id": 519,
            "property_label": "relatedStillImage",
            "thumbnail_title": "09274-01-2007-02_02.jpg",
            "thumbnail_type": "image/jpeg",
            "thumbnail_url": "/files/square/76047662b3549a8959405e3dc083ff5f027d5146.jpg",
            "type": "resource",
            "url": null,
            "value_resource_id": 237149,
            "value_resource_name": "items"
        }
    ],
    "dcepk:sourceIdentifier": [
        {
            "@value": "09274-01-2007-02",
            "is_public": true,
            "property_id": 516,
            "property_label": "ソースID",
            "type": "literal"
        }
    ],
    "dcepk:titleTranscription": [
        {
            "@language": "ja",
            "@value": "ぺんだんといぶ",
            "is_public": true,
            "property_id": 517,
            "property_label": "公演名よみ",
            "type": "literal"
        }
    ],
    "dcterms:abstract": [
        {
            "@language": "ja",
            "@value": "傍観を許さない、目と心を奪う強靭なダンサーとダンス・BATIK＝黒田育世新作。舞台。大きく円形に張り出し。後方横幅一杯にトタンの壁。\r\n構成。ワイヤで浮遊、穏やかに口笛を吹く育チャンは、母に呼ばれ喜び。しかし、他の子に依る母をみて、激しく嘆き、痙攣。母のスカート下で治まる。が安息も一時。母の心はしばし離れ、子は孤独な自分に出会うこととなる。愛されつつ疎まれる、母を感じながら失い続けていく、痛切な幼児体験。な、母(黒田)、育ちゃん(清家)の関係性を、妄想膨大な分身達とともに描く。\r\nどっぷり「黒田育世」漬け。痛切な魂の叫びなダンスに震えるねこ。泣き、叫び、笑い、さ迷う、少女期の黒田。起伏激しい思慕の念、母との関係性をソロ、群舞で劇的に展開。モチーフを繰り返しながらも、絶えず変化するフォーメイション、陰影ある照明ら効果で失速知らず。蛍光雪舞う圧巻のラストまで、出ずっぱりぶっちぎりで駈け抜け。黒田に付き従う、カンパニの結束力もまた圧巻なり。",
            "is_public": true,
            "property_id": 19,
            "property_label": "Abstract",
            "type": "literal"
        },
        {
            "@language": "en",
            "@value": "A new work by BATIK’s Ikuyo Kuroda does not allow you to stand on the sidelines, but captures your eyes and heart with resilient dancers and dance.\r\nStage. A circular stage thrusts into the house. A tin wall fills the entire width upstage. \r\n\r\nStructure. A child, Iku-chan, hanging on wires, whistling softly, was delighted to be called by her mother. But when she sees her mother paying attention to another child, she cries bitterly and goes into convulsions. She crawls under her mother’s skirt and becomes calm. But her repose is only temporary. Her mother’s heart often leaves her and she encounters her lonely self. A painful childhood experience in which the child sometimes loses her mother’s attention and alternately feels loved and neglected. The relationship between the mother (Kuroda) and Iku-chan (Seike) is portrayed with a vast array of performers depicting delusional alter egos.\r\n\r\nThis piece is totally “Ikuyo Kuroda.” A cat trembles at the dance of a crying painful soul. A young Kuroda cries, screams, laughs and strays. The intense ups and downs of her feelings and relationship with her mother dramatically unfold in both solo and ensemble dances. While motifs are repeated, the ever-changing formations and effects, including shadowy lighting, keeps the performance fast-paced. Kuroda, who is on stage throughout the piece, races around at full speed until the spectacular final scene, filled with fluorescent snow. The bond of the dancers that follow Kuroda is also remarkable.",
            "is_public": true,
            "property_id": 19,
            "property_label": "Abstract",
            "type": "literal"
        }
    ],
    "dcterms:date": [
        {
            "@value": "2007",
            "is_public": true,
            "property_id": 7,
            "property_label": "Date",
            "type": "literal"
        }
    ],
    "dcterms:identifier": [
        {
            "@value": "09274-01-2007-02",
            "is_public": true,
            "property_id": 10,
            "property_label": "Identifier",
            "type": "literal"
        },
        {
            "@value": "09274-01-2007-02",
            "is_public": true,
            "property_id": 10,
            "property_label": "Identifier",
            "type": "literal"
        }
    ],
    "dcterms:subject": [
        {
            "@language": "ja",
            "@value": "コンテンポラリーダンス",
            "is_public": true,
            "property_id": 3,
            "property_label": "Subject",
            "type": "literal"
        },
        {
            "@language": "en",
            "@value": "contemporary dance",
            "is_public": true,
            "property_id": 3,
            "property_label": "Subject",
            "type": "literal"
        }
    ],
    "dcterms:temporal": [
        {
            "@value": "2007/3/29",
            "is_public": true,
            "property_id": 41,
            "property_label": "Temporal Coverage",
            "type": "literal"
        }
    ],
    "dcterms:title": [
        {
            "@language": "ja",
            "@value": "ペンダント・イヴ",
            "is_public": true,
            "property_id": 1,
            "property_label": "Title",
            "type": "literal"
        },
        {
            "@language": "en",
            "@value": "Pendanteve",
            "is_public": true,
            "property_id": 1,
            "property_label": "Title",
            "type": "literal"
        }
    ],
    "dcterms:type": [
        {
            "@value": "http://purl.org/dc/dcmitype/Event",
            "is_public": true,
            "property_id": 8,
            "property_label": "Type",
            "type": "literal"
        }
    ],
    "o:created": {
        "@type": "http://www.w3.org/2001/XMLSchema#dateTime",
        "@value": "2021-02-19T12:27:15+00:00"
    },
    "o:id": 238609,
    "o:is_public": true,
    "o:item_set": [],
    "o:media": [],
    "o:modified": {
        "@type": "http://www.w3.org/2001/XMLSchema#dateTime",
        "@value": "2021-02-19T13:56:28+00:00"
    },
    "o:owner": {
        "@id": "http://enpaku-jdta.jp/api/users/1",
        "o:id": 1
    },
    "o:resource_class": {
        "@id": "http://enpaku-jdta.jp/api/resource_classes/306",
        "o:id": 306
    },
    "o:resource_template": {
        "@id": "http://enpaku-jdta.jp/api/resource_templates/2",
        "o:id": 2
    },
    "o:site": [
        {
            "@id": "http://enpaku-jdta.jp/api/sites/1",
            "o:id": 1
        }
    ],
    "o:thumbnail": null,
    "o:title": "ペンダント・イヴ",
    "thumbnail_display_urls": {
        "large": null,
        "medium": null,
        "square": null
    }
}